sppenv/__init__.py
sppenv/penv.py
sppenv-0.1.1.dist-info/WHEEL
sppenv-0.1.1.dist-info/METADATA
sppenv-0.1.1.dist-info/RECORD
